django_simple_proxy/__init__.py
django_simple_proxy/admin.py
django_simple_proxy/migrations/0001_initial.py
django_simple_proxy/migrations/__init__.py
django_simple_proxy/models.py
django_simple_proxy/queryset.py
django_simple_proxy/tasks.py
django_simple_proxy/tools/__init__.py
django_simple_proxy/tools/check.py
django_simple_proxy/tools/tools.py
django_simple_proxy/tools/useragent.py
django_simple_proxy-0.1.5.dist-info/LICENSE
django_simple_proxy-0.1.5.dist-info/WHEEL
django_simple_proxy-0.1.5.dist-info/METADATA
django_simple_proxy-0.1.5.dist-info/RECORD
