Metadata-Version: 2.1
Name: django-simple-proxy
Version: 0.1.5
Summary: 
Home-page: https://github.com/volunteer-prb/django_simple_proxy
Keywords: django,proxy
Author: Alex Polev
Author-email: apolevki09@gmail.com
Requires-Python: >=3.7,<4.0
Classifier: Programming Language :: Python :: 3
Classifier: Programming Language :: Python :: 3.10
Classifier: Programming Language :: Python :: 3.7
Classifier: Programming Language :: Python :: 3.8
Classifier: Programming Language :: Python :: 3.9
Requires-Dist: Django
Requires-Dist: django-import-export
Requires-Dist: requests
Project-URL: Repository, https://github.com/volunteer-prb/django_simple_proxy
